{
  "statistical_data": {
    "friends_num": 3,
    "active_num": 2,
    "error_num": 1,
    "article_num": 10,
    "last_updated_time": "2025-06-19 14:19:25"
  },
  "article_data": [
    {
      "title": "我的 WordPress 博客主题与插件设置分享",
      "created": "2025-06-17 00:58",
      "link": "https://veryjack.com/technique/about_my_blog_theme/",
      "author": "veryjack",
      "avatar": "https://bu.dusays.com/2023/10/11/652621ea4624d.jpg"
    },
    {
      "title": "又一个 WordPress 友情链接插件",
      "created": "2025-06-07 13:08",
      "link": "https://veryjack.com/technique/wordpress_friendlinks_plugin/",
      "author": "veryjack",
      "avatar": "https://bu.dusays.com/2023/10/11/652621ea4624d.jpg"
    },
    {
      "title": "集合！我的AI员工们",
      "created": "2025-06-02 22:27",
      "link": "https://veryjack.com/technique/my_ai_employees/",
      "author": "veryjack",
      "avatar": "https://bu.dusays.com/2023/10/11/652621ea4624d.jpg"
    },
    {
      "title": "才不到 300？OPPO Enco Free 4 主观体验",
      "created": "2025-05-17 23:42",
      "link": "https://veryjack.com/technique/enco_free_4/",
      "author": "veryjack",
      "avatar": "https://bu.dusays.com/2023/10/11/652621ea4624d.jpg"
    },
    {
      "title": "与其内耗，不如去山里 —— 四明山",
      "created": "2025-05-06 23:01",
      "link": "https://veryjack.com/photograph/simingshan/",
      "author": "veryjack",
      "avatar": "https://bu.dusays.com/2023/10/11/652621ea4624d.jpg"
    },
    {
      "title": "2024年终总结",
      "created": "2024-09-17 19:04",
      "link": "https://bokebo.com/archives/2188",
      "author": "bokebo",
      "avatar": "https://bu.dusays.com/2023/10/11/652621c4b2531.png"
    },
    {
      "title": "寻找王先生",
      "created": "2024-07-08 14:45",
      "link": "https://bokebo.com/archives/1787",
      "author": "bokebo",
      "avatar": "https://bu.dusays.com/2023/10/11/652621c4b2531.png"
    },
    {
      "title": "未来的一些计划",
      "created": "2024-04-26 21:54",
      "link": "https://bokebo.com/archives/1577",
      "author": "bokebo",
      "avatar": "https://bu.dusays.com/2023/10/11/652621c4b2531.png"
    },
    {
      "title": "说说我对于朋友圈的看法",
      "created": "2024-01-15 09:05",
      "link": "https://bokebo.com/archives/126",
      "author": "bokebo",
      "avatar": "https://bu.dusays.com/2023/10/11/652621c4b2531.png"
    },
    {
      "title": "2023年终总结",
      "created": "2023-12-29 20:08",
      "link": "https://bokebo.com/archives/1373",
      "author": "bokebo",
      "avatar": "https://bu.dusays.com/2023/10/11/652621c4b2531.png"
    }
  ]
}